vectome/__init__.py
vectome/caching.py
vectome/cli.py
vectome/edits.py
vectome/genomes.py
vectome/http.py
vectome/names.py
vectome/ncbi.py
vectome/sketching.py
vectome/vectorize.py
vectome/data/__init__.py
vectome/data/download.py
vectome/data/landmarks.yml
vectome/data/manifest.py
vectome/data/lists/strain-list-113-taxid.txt
vectome/data/lists/strain-list-ENA2018-bacteria-100.txt
vectome/data/lists/strain-list-ENA2018-bacteria-10k.txt
vectome/data/lists/strain-list-ENA2018-bacteria-1_per_genus.txt
vectome/data/lists/strain-list-ENA2018-bacteria-1_per_species.txt
vectome/data/lists/strain-list-ENA2018-bacteria-1k.txt
vectome/data/lists/strain-list-ENA2018-bacteria-50.txt
vectome/data/lists/strain-list-ENA2018-bacteria-661k.txt
vectome/data/lists/strain-list-report-taxid.txt
vectome/data/sketches/GCF_000195955.2.fna.gz_n=10000_k=21.sig
vectome/data/sketches/GCF_001559675.1.fna.gz_n=10000_k=21.sig
vectome/data/sketches/GCF_022370415.1.fna.gz_n=10000_k=21.sig
vectome/data/sketches/GCF_022869665.1.fna.gz_n=10000_k=21.sig
vectome/data/sketches/SAMEA104034609.contigs.fa.gz_n=10000_k=21.sig
vectome/data/sketches/SAMEA104034772.contigs.fa.gz_n=10000_k=21.sig
vectome/data/sketches/SAMEA104105611.contigs.fa.gz_n=10000_k=21.sig
vectome/data/sketches/SAMEA104600300.contigs.fa.gz_n=10000_k=21.sig
vectome/data/sketches/SAMEA2056051.contigs.fa.gz_n=10000_k=21.sig
vectome/data/sketches/SAMEA2074349.contigs.fa.gz_n=10000_k=21.sig
vectome/data/sketches/SAMEA2160413.contigs.fa.gz_n=10000_k=21.sig
vectome/data/sketches/SAMEA2246879.contigs.fa.gz_n=10000_k=21.sig
vectome/data/sketches/SAMEA2734446.contigs.fa.gz_n=10000_k=21.sig
vectome/data/sketches/SAMEA3357287.contigs.fa.gz_n=10000_k=21.sig
vectome/data/sketches/SAMEA3572871.contigs.fa.gz_n=10000_k=21.sig
vectome/data/sketches/SAMEA3894888.contigs.fa.gz_n=10000_k=21.sig
vectome/data/sketches/SAMEA3930586.contigs.fa.gz_n=10000_k=21.sig
vectome/data/sketches/SAMEA4008704.contigs.fa.gz_n=10000_k=21.sig
vectome-0.0.6.dist-info/licenses/LICENSE
vectome-0.0.6.dist-info/METADATA
vectome-0.0.6.dist-info/WHEEL
vectome-0.0.6.dist-info/entry_points.txt
vectome-0.0.6.dist-info/top_level.txt
vectome-0.0.6.dist-info/RECORD
