Metadata-Version: 2.4
Name: vectome
Version: 0.0.6
Summary: Deterministic vectorization of genomes.
Author-email: Eachan Johnson <eachan.johnson@crick.ac.uk>
License: MIT License
Project-URL: Homepage, https://github.com/scbirlab/vectome
Project-URL: Bug Tracker, https://github.com/scbirlab/vectome/issues
Keywords: template
Classifier: Development Status :: 3 - Alpha
Classifier: License :: OSI Approved :: MIT License
Classifier: Programming Language :: Python :: 3.10
Classifier: Programming Language :: Python :: 3.11
Classifier: Programming Language :: Python :: 3.12
Classifier: Programming Language :: Python :: 3.13
Classifier: Programming Language :: Python :: 3 :: Only
Requires-Python: >=3.10
License-File: LICENSE
Requires-Dist: bioino
Requires-Dist: carabiner-tools>=0.0.4
Requires-Dist: joblib
Requires-Dist: numpy
Requires-Dist: platformdirs>=4.4.0
Requires-Dist: pyyaml
Requires-Dist: requests
Requires-Dist: sourmash
Requires-Dist: tqdm
Provides-Extra: all
Provides-Extra: dev
Requires-Dist: pytest; extra == "dev"
Requires-Dist: flake8; extra == "dev"
Dynamic: license-file
